{
    "info": {
        "stock": "fujifilm_pro_400h",
        "name": "Fujifilm Pro 400H",
        "type": "negative",
        "color": true,
        "densitometer": "status_M",
        "log_sensitivity_density_over_min": 1.0,
        "reference_illuminant": "D65",
        "viewing_illuminant": "D50"
    },
    "data": {
        "log_sensitivity": [
            [
                NaN,
                NaN,
                NaN
            ],
            [
                NaN,
                NaN,
                -0.7205656517565754
            ],
            [
                NaN,
                NaN,
                -0.274891529541598
            ],
            [
                NaN,
                NaN,
                0.260428565556908
            ],
            [
                NaN,
                NaN,
                0.7701352650070885
            ],
            [
                NaN,
                NaN,
                1.1227498735990165
            ],
            [
                NaN,
                NaN,
                1.2795568901603247
            ],
            [
                NaN,
                NaN,
                1.3316843726317198
            ],
            [
                NaN,
                NaN,
                1.3479806037665096
            ],
            [
                NaN,
                NaN,
                1.3488990108359826
            ],
            [
                NaN,
                NaN,
                1.3424682649957809
            ],
            [
                NaN,
                NaN,
                1.3316109007559473
            ],
            [
                NaN,
                NaN,
                1.3190722776447952
            ],
            [
                NaN,
                NaN,
                1.3087859098737584
            ],
            [
                NaN,
                NaN,
                1.3098672377167884
            ],
            [
                NaN,
                -0.7178801760214613,
                1.3269089782362418
            ],
            [
                NaN,
                -0.6479588908817863,
                1.3803753600855548
            ],
            [
                NaN,
                -0.5751445359286828,
                1.4646248543564406
            ],
            [
                NaN,
                -0.49878131665912395,
                1.521119508016686
            ],
            [
                NaN,
                -0.37020435806460517,
                1.4305046173733582
            ],
            [
                NaN,
                -0.17140887308930988,
                1.1397247731763547
            ],
            [
                NaN,
                0.053898862665994036,
                0.7673894116678901
            ],
            [
                NaN,
                0.2894440552621754,
                0.41069946686935027
            ],
            [
                NaN,
                0.5040434317880028,
                0.15518718474409535
            ],
            [
                NaN,
                0.6951247211036327,
                -0.07015979417902583
            ],
            [
                NaN,
                0.8079812170598462,
                -0.2754087612928729
            ],
            [
                NaN,
                0.899249485147834,
                -0.4547067362978075
            ],
            [
                NaN,
                0.992155653384931,
                -0.619585735833446
            ],
            [
                NaN,
                1.0748907839807085,
                NaN
            ],
            [
                NaN,
                1.1507321711329859,
                NaN
            ],
            [
                NaN,
                1.2142055790724073,
                NaN
            ],
            [
                NaN,
                1.2610734819344422,
                NaN
            ],
            [
                NaN,
                1.2989867923710743,
                NaN
            ],
            [
                NaN,
                1.3287872249297419,
                NaN
            ],
            [
                NaN,
                1.3475751439751664,
                NaN
            ],
            [
                NaN,
                1.3513288755541513,
                NaN
            ],
            [
                -0.6019820568654511,
                1.3175402957154287,
                NaN
            ],
            [
                -0.4187999488945337,
                1.2227135287973154,
                NaN
            ],
            [
                -0.22046221505682015,
                1.064014357882387,
                NaN
            ],
            [
                0.034575282157517984,
                0.7866192568629625,
                NaN
            ],
            [
                0.271564356610697,
                0.4598485904815012,
                NaN
            ],
            [
                0.49604678782897166,
                0.07304197337847305,
                NaN
            ],
            [
                0.6925296625532911,
                -0.3673418726328253,
                NaN
            ],
            [
                0.8686794126589719,
                NaN,
                NaN
            ],
            [
                0.9928660222792824,
                NaN,
                NaN
            ],
            [
                1.0469406794635912,
                NaN,
                NaN
            ],
            [
                1.0603131575903666,
                NaN,
                NaN
            ],
            [
                1.0491030916805124,
                NaN,
                NaN
            ],
            [
                1.045859757023709,
                NaN,
                NaN
            ],
            [
                1.055557254612057,
                NaN,
                NaN
            ],
            [
                1.058213469693355,
                NaN,
                NaN
            ],
            [
                1.0333492253048582,
                NaN,
                NaN
            ],
            [
                0.955188820386437,
                NaN,
                NaN
            ],
            [
                0.7572301943702001,
                NaN,
                NaN
            ],
            [
                0.4746995688045333,
                NaN,
                NaN
            ],
            [
                0.14172397637069045,
                NaN,
                NaN
            ],
            [
                -0.217515808727447,
                NaN,
                NaN
            ],
            [
                NaN,
                NaN,
                NaN
            ],
            [
                NaN,
                NaN,
                NaN
            ],
            [
                NaN,
                NaN,
                NaN
            ],
            [
                NaN,
                NaN,
                NaN
            ],
            [
                NaN,
                NaN,
                NaN
            ],
            [
                NaN,
                NaN,
                NaN
            ],
            [
                NaN,
                NaN,
                NaN
            ],
            [
                NaN,
                NaN,
                NaN
            ],
            [
                NaN,
                NaN,
                NaN
            ],
            [
                NaN,
                NaN,
                NaN
            ],
            [
                NaN,
                NaN,
                NaN
            ],
            [
                NaN,
                NaN,
                NaN
            ],
            [
                NaN,
                NaN,
                NaN
            ],
            [
                NaN,
                NaN,
                NaN
            ],
            [
                NaN,
                NaN,
                NaN
            ],
            [
                NaN,
                NaN,
                NaN
            ],
            [
                NaN,
                NaN,
                NaN
            ],
            [
                NaN,
                NaN,
                NaN
            ],
            [
                NaN,
                NaN,
                NaN
            ],
            [
                NaN,
                NaN,
                NaN
            ],
            [
                NaN,
                NaN,
                NaN
            ],
            [
                NaN,
                NaN,
                NaN
            ],
            [
                NaN,
                NaN,
                NaN
            ],
            [
                NaN,
                NaN,
                NaN
            ]
        ],
        "wavelengths": [
            380.0,
            385.0,
            390.0,
            395.0,
            400.0,
            405.0,
            410.0,
            415.0,
            420.0,
            425.0,
            430.0,
            435.0,
            440.0,
            445.0,
            450.0,
            455.0,
            460.0,
            465.0,
            470.0,
            475.0,
            480.0,
            485.0,
            490.0,
            495.0,
            500.0,
            505.0,
            510.0,
            515.0,
            520.0,
            525.0,
            530.0,
            535.0,
            540.0,
            545.0,
            550.0,
            555.0,
            560.0,
            565.0,
            570.0,
            575.0,
            580.0,
            585.0,
            590.0,
            595.0,
            600.0,
            605.0,
            610.0,
            615.0,
            620.0,
            625.0,
            630.0,
            635.0,
            640.0,
            645.0,
            650.0,
            655.0,
            660.0,
            665.0,
            670.0,
            675.0,
            680.0,
            685.0,
            690.0,
            695.0,
            700.0,
            705.0,
            710.0,
            715.0,
            720.0,
            725.0,
            730.0,
            735.0,
            740.0,
            745.0,
            750.0,
            755.0,
            760.0,
            765.0,
            770.0,
            775.0,
            780.0
        ],
        "density_curves": [
            [
                NaN,
                NaN,
                NaN
            ],
            [
                NaN,
                NaN,
                NaN
            ],
            [
                NaN,
                NaN,
                NaN
            ],
            [
                NaN,
                NaN,
                NaN
            ],
            [
                NaN,
                NaN,
                NaN
            ],
            [
                NaN,
                NaN,
                NaN
            ],
            [
                NaN,
                NaN,
                NaN
            ],
            [
                NaN,
                NaN,
                NaN
            ],
            [
                NaN,
                NaN,
                NaN
            ],
            [
                NaN,
                NaN,
                NaN
            ],
            [
                NaN,
                NaN,
                NaN
            ],
            [
                NaN,
                NaN,
                NaN
            ],
            [
                NaN,
                NaN,
                NaN
            ],
            [
                NaN,
                NaN,
                NaN
            ],
            [
                NaN,
                NaN,
                NaN
            ],
            [
                NaN,
                NaN,
                NaN
            ],
            [
                NaN,
                NaN,
                NaN
            ],
            [
                NaN,
                NaN,
                NaN
            ],
            [
                NaN,
                NaN,
                NaN
            ],
            [
                NaN,
                NaN,
                NaN
            ],
            [
                NaN,
                NaN,
                NaN
            ],
            [
                NaN,
                NaN,
                NaN
            ],
            [
                NaN,
                NaN,
                NaN
            ],
            [
                NaN,
                NaN,
                NaN
            ],
            [
                NaN,
                NaN,
                NaN
            ],
            [
                NaN,
                NaN,
                NaN
            ],
            [
                NaN,
                NaN,
                NaN
            ],
            [
                NaN,
                NaN,
                NaN
            ],
            [
                NaN,
                NaN,
                NaN
            ],
            [
                0.1732334961040523,
                0.6877192501446029,
                0.9493948970924898
            ],
            [
                0.1727984046796168,
                0.6871274938339986,
                0.948960711095412
            ],
            [
                0.17244654553678146,
                0.6865338619349578,
                0.9484585610884386
            ],
            [
                0.17249395660609868,
                0.6858931335505202,
                0.9484409140262016
            ],
            [
                0.1721409533326958,
                0.685325851296956,
                0.9484666676442637
            ],
            [
                0.17165659083634954,
                0.6848008086197969,
                0.9484972171924967
            ],
            [
                0.17170160780410493,
                0.6842462917671904,
                0.9484926643843167
            ],
            [
                0.1717532417433544,
                0.6837754259880373,
                0.9479638553595146
            ],
            [
                0.17166212472767764,
                0.6833572624821806,
                0.9476620208189792
            ],
            [
                0.17176026856715154,
                0.6829566932296878,
                0.9477560481163492
            ],
            [
                0.17226808578961972,
                0.6826041240780714,
                0.9477523544371074
            ],
            [
                0.17242345587383714,
                0.6823313250424375,
                0.947733883637121
            ],
            [
                0.17253989753841398,
                0.6820512128486205,
                0.9480505509461669
            ],
            [
                0.17297651460011446,
                0.6818011720779453,
                0.9484780448089917
            ],
            [
                0.17336392373755208,
                0.6817811714438154,
                0.9484427073311398
            ],
            [
                0.17378490675642957,
                0.6818206692833638,
                0.9487559892402098
            ],
            [
                0.17432779091318037,
                0.6817826023457775,
                0.9493189303092505
            ],
            [
                0.17496616088085123,
                0.6817806055341428,
                0.9497256178970883
            ],
            [
                0.17564092836683057,
                0.6821112505986321,
                0.9502668887934403
            ],
            [
                0.17638716958045594,
                0.6824502883706287,
                0.9509910489397289
            ],
            [
                0.17723299804251252,
                0.6827503419747082,
                0.9518122539444728
            ],
            [
                0.1781657348725863,
                0.6832821148023619,
                0.9526826960972954
            ],
            [
                0.1791742653135711,
                0.6838724257102806,
                0.9537072825666932
            ],
            [
                0.18025278447485812,
                0.6845395158371949,
                0.9549353479355842
            ],
            [
                0.18143837426945622,
                0.6853666195310814,
                0.9563085695180302
            ],
            [
                0.1827738562204216,
                0.68634189390282,
                0.9577517321388475
            ],
            [
                0.18413978154999391,
                0.6874468832539115,
                0.9593991237412743
            ],
            [
                0.1856122982471973,
                0.6886974611055346,
                0.9612930553518448
            ],
            [
                0.187279812581204,
                0.6901166460940759,
                0.9633976656161811
            ],
            [
                0.18900170789760926,
                0.6917064381785045,
                0.9656911071887447
            ],
            [
                0.190855973243519,
                0.6935151046696434,
                0.9681959867155705
            ],
            [
                0.19288617398824792,
                0.695575568980606,
                0.970978992155775
            ],
            [
                0.1950403057058276,
                0.6978880511846973,
                0.9741006494947434
            ],
            [
                0.19731842263597907,
                0.7004538985122996,
                0.9775514715409453
            ],
            [
                0.1998298707932132,
                0.7033366807532107,
                0.9813162761446126
            ],
            [
                0.20255396508836118,
                0.706626647596401,
                0.985458192748796
            ],
            [
                0.20535883677871708,
                0.7103971197963369,
                0.9900905140572083
            ],
            [
                0.2084925958100223,
                0.7146820824402151,
                0.9952300510222792
            ],
            [
                0.21188882064984235,
                0.7195964764902139,
                1.000981207587224
            ],
            [
                0.21558313723115,
                0.7253646226108885,
                1.0074430567155581
            ],
            [
                0.22017299129637463,
                0.7322701164501174,
                1.0146741494530949
            ],
            [
                0.2258581915256026,
                0.74043452648196,
                1.0229685995178142
            ],
            [
                0.2325138647030305,
                0.7495307770211445,
                1.0322618124515184
            ],
            [
                0.2399656615335993,
                0.759103512756295,
                1.0421827624822884
            ],
            [
                0.24826736174169114,
                0.7692248469133126,
                1.0524570010568635
            ],
            [
                0.25725275087083516,
                0.7798921333970724,
                1.0630641118284112
            ],
            [
                0.2667881194055352,
                0.7909715025688078,
                1.0740415276643183
            ],
            [
                0.27690801180985736,
                0.8023239537474253,
                1.085360015803927
            ],
            [
                0.28759648136776333,
                0.8140298783722643,
                1.0969433066645358
            ],
            [
                0.29878600906281416,
                0.8260766406550367,
                1.108988134254647
            ],
            [
                0.31039663763102676,
                0.8384039913187069,
                1.1215719324524207
            ],
            [
                0.3223763105363693,
                0.8510072694766888,
                1.134472173382567
            ],
            [
                0.33471377643913414,
                0.8638258135113498,
                1.1478197878665966
            ],
            [
                0.34740345034333214,
                0.8769370728532132,
                1.161239763650293
            ],
            [
                0.36043157306310875,
                0.8903325716903986,
                1.1744820470710475
            ],
            [
                0.3737709276345093,
                0.9036145503400567,
                1.1882863164191613
            ],
            [
                0.3873479851828433,
                0.9171828900812022,
                1.2024706412588764
            ],
            [
                0.4011800514314384,
                0.9311927339399139,
                1.2168159635499929
            ],
            [
                0.4153432945820975,
                0.9452415528352145,
                1.2314476834008363
            ],
            [
                0.42970031849524015,
                0.9594427604535755,
                1.246428215242086
            ],
            [
                0.44421918472326666,
                0.9738027839279751,
                1.261718588591631
            ],
            [
                0.4589443239642934,
                0.9882698136321119,
                1.2771975179992523
            ],
            [
                0.47387448688537565,
                1.002893461643132,
                1.2927023410349958
            ],
            [
                0.4889152876312674,
                1.0176416540670827,
                1.308112636430415
            ],
            [
                0.5041154138088731,
                1.0325101282690068,
                1.3234201731049475
            ],
            [
                0.519554832677558,
                1.0475156829127032,
                1.3386623842120924
            ],
            [
                0.5350966839493594,
                1.0626321790822288,
                1.3538289394095269
            ],
            [
                0.5507352700582272,
                1.0778952276888545,
                1.3689261769049137
            ],
            [
                0.5665066323163012,
                1.0932627983163308,
                1.3839758316033541
            ],
            [
                0.5824122925043705,
                1.1087365697661307,
                1.3989993765406783
            ],
            [
                0.5984335446968269,
                1.1247453996230412,
                1.4139968251430295
            ],
            [
                0.6145280878386064,
                1.1410424646439745,
                1.428952842529773
            ],
            [
                0.6307045610005687,
                1.1571730108006653,
                1.4438651940277323
            ],
            [
                0.6470207609096029,
                1.1730982627172561,
                1.4587504137138874
            ],
            [
                0.6633471126960659,
                1.1890462541087743,
                1.473602784147789
            ],
            [
                0.6797361722194866,
                1.20510726533925,
                1.48843499278835
            ],
            [
                0.6962962346892863,
                1.2212500829655137,
                1.5032528077957297
            ],
            [
                0.7128837663159098,
                1.2375091547617856,
                1.518032715741734
            ],
            [
                0.7294898949145393,
                1.2538199744472305,
                1.5328181027356045
            ],
            [
                0.7461619899008212,
                1.270120256152033,
                1.5475801834899046
            ],
            [
                0.7629124857376672,
                1.286390071656326,
                1.56227129053066
            ],
            [
                0.7796919412152716,
                1.3025968299272133,
                1.577001621203616
            ],
            [
                0.7965095443113841,
                1.3187595175821663,
                1.591723403123898
            ],
            [
                0.813369680269069,
                1.3348966779664095,
                1.6063893482571898
            ],
            [
                0.8302353530790072,
                1.3509873049150865,
                1.6210476172513373
            ],
            [
                0.8471569588013604,
                1.3670312024973674,
                1.6356883992808349
            ],
            [
                0.8641293771672671,
                1.3830339423519353,
                1.6503250280649286
            ],
            [
                0.8811058002211887,
                1.3989908121532388,
                1.6649605134845835
            ],
            [
                0.89808010083965,
                1.414891127434371,
                1.6795558570049827
            ],
            [
                0.9150645091235687,
                1.4308001586420018,
                1.6941650763402964
            ],
            [
                0.9320665501198664,
                1.4466770123237505,
                1.7087719146740454
            ],
            [
                0.949083044697103,
                1.4624291048082243,
                1.7233228087062766
            ],
            [
                0.9661109655646306,
                1.4781914708563497,
                1.737880839248955
            ],
            [
                0.9831641537118571,
                1.4939671420613252,
                1.7524131487839891
            ],
            [
                1.0002197961228343,
                1.5096906416970828,
                1.7669276349986363
            ],
            [
                1.0172199134905446,
                1.5253479363236406,
                1.7814890833032486
            ],
            [
                1.034217133638804,
                1.5409937495036738,
                1.795986581130585
            ],
            [
                1.0512514023655202,
                1.5566034513363367,
                1.8104611260398176
            ],
            [
                1.0682905677991987,
                1.5721490848172959,
                1.824979947886405
            ],
            [
                1.085260255238412,
                1.5877064203947233,
                1.8394658310708596
            ],
            [
                1.102298705154373,
                1.6032243177040009,
                1.8539034537604184
            ],
            [
                1.119554573607571,
                1.618675876673493,
                1.8683422874543645
            ],
            [
                1.1370081073177074,
                1.6341043472771875,
                1.8828184334307407
            ],
            [
                1.1543807641893329,
                1.6495328440072312,
                1.8972654465360212
            ],
            [
                1.17146501945519,
                1.6648962209732086,
                1.9116773720602636
            ],
            [
                1.1882993948357063,
                1.6801954202557734,
                1.9260605940450983
            ],
            [
                1.2051140667148403,
                1.6955279658897902,
                1.9404241467858343
            ],
            [
                1.2219154549014937,
                1.7108134175699448,
                1.954848113195279
            ],
            [
                1.2387078700643712,
                1.726035343625485,
                1.9692594428969075
            ],
            [
                1.2554798531839526,
                1.7412396387893248,
                1.983601602644212
            ],
            [
                1.272156296182609,
                1.7564366746669653,
                1.9979728147465257
            ],
            [
                1.2888471260376293,
                1.771580317633596,
                2.0123249203007134
            ],
            [
                1.3055149312221828,
                1.7866695397963952,
                2.0266484248167504
            ],
            [
                1.322037781657848,
                1.801735785519969,
                2.0409796940851623
            ],
            [
                1.3385667826968553,
                1.8167498983593606,
                2.055299608475049
            ],
            [
                1.3550676672472608,
                1.8317479254523648,
                2.069588180827815
            ],
            [
                1.3715044691116176,
                1.8467488141537836,
                2.083852662751334
            ],
            [
                1.3879410206771754,
                1.861703143194332,
                2.0981207698885807
            ],
            [
                1.4042972777186682,
                1.8765698883837518,
                2.1123963142533544
            ],
            [
                1.4205142214100022,
                1.8914018382805688,
                2.126650799875151
            ],
            [
                1.436670759436785,
                1.9062423259668937,
                2.140875388470626
            ],
            [
                1.4529431775740955,
                1.9210303371521709,
                2.155104416042677
            ],
            [
                1.4691163318092086,
                1.9357923922851525,
                2.16932761660594
            ],
            [
                1.4851369299468358,
                1.950505856357235,
                2.1835671058897668
            ],
            [
                1.5011401532304651,
                1.9651367641541637,
                2.1978200390633846
            ],
            [
                1.5170755339803326,
                1.9797807239454275,
                2.211976967020895
            ],
            [
                1.5329138871756416,
                1.9943760044204417,
                2.226063280065738
            ],
            [
                1.5486729190661999,
                2.0088972582096662,
                2.2401553765978464
            ],
            [
                1.5643913672479468,
                2.0234192740042007,
                2.2543136915769426
            ],
            [
                1.5800774739876553,
                2.0378700631618654,
                2.268549769629718
            ],
            [
                1.5956877749013376,
                2.0522569193277227,
                2.282613639904051
            ],
            [
                1.611185350684028,
                2.066626240866741,
                2.2965519273924806
            ],
            [
                1.6265923639327189,
                2.0809675004232857,
                2.3107902464629095
            ],
            [
                1.6419332327425316,
                2.0952627326047475,
                2.3247588799439463
            ],
            [
                1.6572214900241908,
                2.1095200016050315,
                2.3388210270456096
            ],
            [
                1.6724314187709668,
                2.123696863714453,
                2.3534313972182166
            ],
            [
                1.6874895969872605,
                2.13765845335773,
                2.3676506197595644
            ],
            [
                1.702483250286135,
                2.151798808129217,
                2.381990451257274
            ],
            [
                1.717423505694908,
                2.166055290617954,
                2.396416708413519
            ],
            [
                1.7322223798615408,
                2.1798507428651,
                2.4101924261838574
            ],
            [
                1.7470178399587026,
                2.1935701369320832,
                2.4239011759973703
            ],
            [
                1.7616857562840817,
                2.2073502477206084,
                2.4376889157083323
            ],
            [
                1.776155246731234,
                2.2211065749172567,
                2.451442426677067
            ],
            [
                1.7906522450831182,
                2.2348567421788523,
                2.4651948864478435
            ],
            [
                1.8049948659914787,
                2.248653569527772,
                2.47899268674694
            ],
            [
                1.8192673048506982,
                2.262351734910966,
                2.492776657149845
            ],
            [
                1.8335604093899933,
                2.275813540257198,
                2.5064896748484684
            ],
            [
                1.8473980910174144,
                2.289256420690084,
                2.520223430855672
            ],
            [
                1.8612542813920259,
                2.302642014154685,
                2.5340467055868223
            ],
            [
                1.8752636823016446,
                2.3158690156507418,
                2.5477272956797994
            ],
            [
                1.888919745873215,
                2.3289976494931923,
                2.5610259227597147
            ],
            [
                1.9024494217864103,
                2.3423105740684687,
                2.574406153055529
            ],
            [
                1.9162678538859717,
                2.355621138831794,
                2.5880989836664963
            ],
            [
                1.9293719350937721,
                2.3684408044450276,
                2.6011011703613742
            ],
            [
                NaN,
                NaN,
                NaN
            ],
            [
                NaN,
                NaN,
                NaN
            ],
            [
                NaN,
                NaN,
                NaN
            ],
            [
                NaN,
                NaN,
                NaN
            ],
            [
                NaN,
                NaN,
                NaN
            ],
            [
                NaN,
                NaN,
                NaN
            ],
            [
                NaN,
                NaN,
                NaN
            ],
            [
                NaN,
                NaN,
                NaN
            ],
            [
                NaN,
                NaN,
                NaN
            ],
            [
                NaN,
                NaN,
                NaN
            ],
            [
                NaN,
                NaN,
                NaN
            ],
            [
                NaN,
                NaN,
                NaN
            ],
            [
                NaN,
                NaN,
                NaN
            ],
            [
                NaN,
                NaN,
                NaN
            ],
            [
                NaN,
                NaN,
                NaN
            ],
            [
                NaN,
                NaN,
                NaN
            ],
            [
                NaN,
                NaN,
                NaN
            ],
            [
                NaN,
                NaN,
                NaN
            ],
            [
                NaN,
                NaN,
                NaN
            ],
            [
                NaN,
                NaN,
                NaN
            ],
            [
                NaN,
                NaN,
                NaN
            ],
            [
                NaN,
                NaN,
                NaN
            ],
            [
                NaN,
                NaN,
                NaN
            ],
            [
                NaN,
                NaN,
                NaN
            ],
            [
                NaN,
                NaN,
                NaN
            ],
            [
                NaN,
                NaN,
                NaN
            ],
            [
                NaN,
                NaN,
                NaN
            ],
            [
                NaN,
                NaN,
                NaN
            ],
            [
                NaN,
                NaN,
                NaN
            ],
            [
                NaN,
                NaN,
                NaN
            ],
            [
                NaN,
                NaN,
                NaN
            ],
            [
                NaN,
                NaN,
                NaN
            ],
            [
                NaN,
                NaN,
                NaN
            ],
            [
                NaN,
                NaN,
                NaN
            ],
            [
                NaN,
                NaN,
                NaN
            ],
            [
                NaN,
                NaN,
                NaN
            ],
            [
                NaN,
                NaN,
                NaN
            ],
            [
                NaN,
                NaN,
                NaN
            ],
            [
                NaN,
                NaN,
                NaN
            ],
            [
                NaN,
                NaN,
                NaN
            ],
            [
                NaN,
                NaN,
                NaN
            ],
            [
                NaN,
                NaN,
                NaN
            ],
            [
                NaN,
                NaN,
                NaN
            ],
            [
                NaN,
                NaN,
                NaN
            ],
            [
                NaN,
                NaN,
                NaN
            ],
            [
                NaN,
                NaN,
                NaN
            ],
            [
                NaN,
                NaN,
                NaN
            ],
            [
                NaN,
                NaN,
                NaN
            ],
            [
                NaN,
                NaN,
                NaN
            ],
            [
                NaN,
                NaN,
                NaN
            ],
            [
                NaN,
                NaN,
                NaN
            ],
            [
                NaN,
                NaN,
                NaN
            ],
            [
                NaN,
                NaN,
                NaN
            ],
            [
                NaN,
                NaN,
                NaN
            ],
            [
                NaN,
                NaN,
                NaN
            ],
            [
                NaN,
                NaN,
                NaN
            ],
            [
                NaN,
                NaN,
                NaN
            ],
            [
                NaN,
                NaN,
                NaN
            ],
            [
                NaN,
                NaN,
                NaN
            ],
            [
                NaN,
                NaN,
                NaN
            ],
            [
                NaN,
                NaN,
                NaN
            ],
            [
                NaN,
                NaN,
                NaN
            ],
            [
                NaN,
                NaN,
                NaN
            ],
            [
                NaN,
                NaN,
                NaN
            ],
            [
                NaN,
                NaN,
                NaN
            ],
            [
                NaN,
                NaN,
                NaN
            ],
            [
                NaN,
                NaN,
                NaN
            ],
            [
                NaN,
                NaN,
                NaN
            ],
            [
                NaN,
                NaN,
                NaN
            ],
            [
                NaN,
                NaN,
                NaN
            ],
            [
                NaN,
                NaN,
                NaN
            ],
            [
                NaN,
                NaN,
                NaN
            ],
            [
                NaN,
                NaN,
                NaN
            ]
        ],
        "log_exposure": [
            -2.8865756124785724,
            -2.8591246320864157,
            -2.831673651694259,
            -2.804222671302102,
            -2.7767716909099454,
            -2.7493207105177886,
            -2.721869730125632,
            -2.694418749733474,
            -2.6669677693413174,
            -2.6395167889491606,
            -2.612065808557004,
            -2.584614828164847,
            -2.5571638477726903,
            -2.5297128673805336,
            -2.502261886988377,
            -2.47481090659622,
            -2.4473599262040624,
            -2.4199089458119056,
            -2.392457965419749,
            -2.365006985027592,
            -2.3375560046354353,
            -2.3101050242432786,
            -2.282654043851122,
            -2.255203063458965,
            -2.2277520830668083,
            -2.2003011026746506,
            -2.172850122282494,
            -2.145399141890337,
            -2.1179481614981803,
            -2.0904971811060236,
            -2.063046200713867,
            -2.03559522032171,
            -2.0081442399295533,
            -1.9806932595373967,
            -1.953242279145239,
            -1.925791298753082,
            -1.8983403183609253,
            -1.8708893379687686,
            -1.8434383575766118,
            -1.815987377184455,
            -1.7885363967922983,
            -1.7610854164001415,
            -1.7336344360079847,
            -1.706183455615827,
            -1.6787324752236703,
            -1.6512814948315135,
            -1.6238305144393568,
            -1.5963795340472,
            -1.5689285536550432,
            -1.5414775732628865,
            -1.5140265928707297,
            -1.486575612478573,
            -1.4591246320864157,
            -1.431673651694259,
            -1.4042226713021018,
            -1.376771690909945,
            -1.3493207105177882,
            -1.3218697301256315,
            -1.2944187497334747,
            -1.266967769341318,
            -1.2395167889491612,
            -1.212065808557004,
            -1.1846148281648472,
            -1.1571638477726904,
            -1.1297128673805337,
            -1.102261886988377,
            -1.0748109065962197,
            -1.047359926204063,
            -1.0199089458119062,
            -0.9924579654197494,
            -0.9650069850275922,
            -0.9375560046354354,
            -0.9101050242432787,
            -0.8826540438511219,
            -0.8552030634589651,
            -0.8277520830668084,
            -0.8003011026746512,
            -0.7728501222824945,
            -0.7453991418903377,
            -0.717948161498181,
            -0.6904971811060238,
            -0.663046200713867,
            -0.6355952203217102,
            -0.6081442399295536,
            -0.5806932595373968,
            -0.5532422791452395,
            -0.5257912987530827,
            -0.49834031836092596,
            -0.4708893379687692,
            -0.44343835757661243,
            -0.4159873771844552,
            -0.38853639679229846,
            -0.3610854164001417,
            -0.3336344360079849,
            -0.3061834556158277,
            -0.27873247522367095,
            -0.2512814948315142,
            -0.22383051443935742,
            -0.19637953404720065,
            -0.16892855365504345,
            -0.14147757326288668,
            -0.11402659287072991,
            -0.08657561247857315,
            -0.05912463208641594,
            -0.031673651694259175,
            -0.004222671302102299,
            0.023228309090054466,
            0.05067928948221123,
            0.07813026987436844,
            0.1055812502665252,
            0.13303223065868197,
            0.16048321105083874,
            0.1879341914429954,
            0.2153851718351526,
            0.24283615222730937,
            0.27028713261946613,
            0.2977381130116229,
            0.3251890934037801,
            0.35264007379593687,
            0.38009105418809364,
            0.4075420345802504,
            0.43499301497240717,
            0.4624439953645644,
            0.48989497575672114,
            0.5173459561488779,
            0.5447969365410347,
            0.572247916933192,
            0.5996988973253488,
            0.6271498777175055,
            0.6546008581096623,
            0.682051838501819,
            0.7095028188939763,
            0.7369537992861329,
            0.7644047796782897,
            0.7918557600704464,
            0.8193067404626037,
            0.8467577208547604,
            0.8742087012469172,
            0.901659681639074,
            0.9291106620312307,
            0.9565616424233879,
            0.9840126228155447,
            1.0114636032077016,
            1.0389145835998583,
            1.0663655639920153,
            1.093816544384172,
            1.1212675247763288,
            1.1487185051684856,
            1.1761694855606424,
            1.2036204659527994,
            1.2310714463449561,
            1.2585224267371138,
            1.2859734071292706,
            1.3134243875214273,
            1.340875367913584,
            1.3683263483057408,
            1.3957773286978976,
            1.4232283090900544,
            1.4506792894822111,
            1.478130269874368,
            1.505581250266526,
            1.5330322306586828,
            1.5604832110508395,
            1.5879341914429963,
            1.615385171835153,
            1.6428361522273098,
            1.6702871326194666,
            1.6977381130116234,
            1.7251890934037801,
            1.752640073795937,
            1.780091054188094,
            1.8075420345802509,
            1.8349930149724076,
            1.8624439953645644,
            1.8898949757567212,
            1.917345956148878,
            1.9447969365410347,
            1.9722479169331915,
            1.9996988973253482,
            2.027149877717506,
            2.0546008581096626,
            2.08205183850182,
            2.1095028188939766,
            2.1369537992861334,
            2.16440477967829,
            2.191855760070447,
            2.2193067404626037,
            2.2467577208547604,
            2.274208701246918,
            2.301659681639075,
            2.3291106620312316,
            2.3565616424233884,
            2.384012622815545,
            2.411463603207702,
            2.4389145835998587,
            2.4663655639920155,
            2.493816544384172,
            2.52126752477633,
            2.5487185051684866,
            2.5761694855606434,
            2.6036204659528,
            2.631071446344957,
            2.6585224267371137,
            2.6859734071292705,
            2.7134243875214272,
            2.740875367913584,
            2.7683263483057416,
            2.7957773286978984,
            2.823228309090055,
            2.850679289482212,
            2.8781302698743687,
            2.9055812502665255,
            2.9330322306586822,
            2.960483211050839,
            2.9879341914429958,
            3.0153851718351534,
            3.04283615222731,
            3.070287132619467,
            3.0977381130116237,
            3.1251890934037805,
            3.1526400737959372,
            3.180091054188094,
            3.207542034580251,
            3.2349930149724075,
            3.2624439953645643,
            3.289894975756722,
            3.3173459561488787,
            3.3447969365410355,
            3.3722479169331923,
            3.399698897325349,
            3.427149877717506,
            3.4546008581096626,
            3.4820518385018193,
            3.509502818893976,
            3.5369537992861337,
            3.5644047796782905,
            3.5918557600704473,
            3.619306740462604,
            3.646757720854761,
            3.6742087012469176,
            3.7016596816390743,
            3.729110662031231,
            3.756561642423388,
            3.7840126228155455,
            3.8114636032077023,
            3.838914583599859,
            3.866365563992016,
            3.8938165443841726,
            3.9212675247763293,
            3.948718505168486,
            3.976169485560643,
            4.0036204659528,
            4.031071446344957,
            4.058522426737114,
            4.085973407129271,
            4.113424387521428
        ],
        "dye_density": [
            [
                NaN,
                NaN,
                NaN,
                NaN,
                NaN
            ],
            [
                0.28696623834007706,
                0.05088955659563777,
                0.27109017590653783,
                NaN,
                NaN
            ],
            [
                0.28224857399797143,
                0.04693278549192424,
                0.32301300451080484,
                NaN,
                NaN
            ],
            [
                0.27337798388736395,
                0.04305270918513677,
                0.3907553779311547,
                NaN,
                NaN
            ],
            [
                0.2552713155680667,
                0.04005334407439767,
                0.4691446455479718,
                1.4474596588805715,
                NaN
            ],
            [
                0.23060536018638303,
                0.038963419114251406,
                0.5438126468070426,
                1.205072027039434,
                1.7735880705636469
            ],
            [
                0.2048823943808031,
                0.03921330390718004,
                0.6189085703098265,
                1.0793323229332723,
                1.650197876901723
            ],
            [
                0.18328641710235713,
                0.041117659139513915,
                0.6936957823691838,
                1.0414543210213876,
                1.6560258611608694
            ],
            [
                0.16494957376801425,
                0.043251330807982394,
                0.7673890920238411,
                1.031633313347948,
                1.7028680581212228
            ],
            [
                0.14872808162752202,
                0.04633254738604547,
                0.8345239443370526,
                1.034387994687197,
                1.770702474372011
            ],
            [
                0.13370596618538477,
                0.04926130417629074,
                0.8985431101617559,
                1.0367987832005559,
                1.8316817073819451
            ],
            [
                0.11907067585563748,
                0.05277492607415739,
                0.9433710433175377,
                1.036340003815561,
                1.8739291109669747
            ],
            [
                0.10910651892856102,
                0.05628229899395858,
                0.9758912808231534,
                1.0304031616030738,
                1.8995590841616692
            ],
            [
                0.09795536635869828,
                0.05957888686135541,
                0.9930135828448918,
                1.0204141541458018,
                1.9113481678657624
            ],
            [
                0.08903357571930649,
                0.06506574863762334,
                0.9990864480323267,
                1.0057417749720552,
                1.9120886273138678
            ],
            [
                0.08223139055716525,
                0.07257042665688108,
                0.988330103602824,
                0.9939350311916362,
                1.9029477601531632
            ],
            [
                0.07503563842858825,
                0.08999168693901533,
                0.9572381129745644,
                0.9773088430793339,
                1.8822499787350417
            ],
            [
                0.0691872449472585,
                0.10872396867312671,
                0.9142359550120547,
                0.9590321385546691,
                1.8482179660505405
            ],
            [
                0.06410451871533776,
                0.12943677686487978,
                0.8544025191062516,
                0.9405146268180011,
                1.7993589249188777
            ],
            [
                0.05859282213049809,
                0.1489610761740023,
                0.785882758712719,
                0.9213482891530747,
                1.7349426931769567
            ],
            [
                0.05413082916573078,
                0.1824168869482157,
                0.7063373970741866,
                0.9016551898143808,
                1.6769160032474941
            ],
            [
                0.04912669302700301,
                0.22503987372932777,
                0.6241370756523681,
                0.8818230389882333,
                1.627785308786282
            ],
            [
                0.04654807909499127,
                0.27904351525123455,
                0.5485659782138327,
                0.8620214649276832,
                1.5830995832867627
            ],
            [
                0.04379794363535146,
                0.33530711770437815,
                0.47330875713252174,
                0.8429233415461009,
                1.5469096037598113
            ],
            [
                0.04237147555210187,
                0.40024125682707684,
                0.3990258133625877,
                0.8261922597034611,
                1.5230593123076437
            ],
            [
                0.041426986958511464,
                0.4706762989277415,
                0.33240117828934,
                0.8132588798710918,
                1.5113150126050647
            ],
            [
                0.04184611853108646,
                0.554970423772749,
                0.27283125632914884,
                0.8010300212666635,
                1.514782462956771
            ],
            [
                0.043776136436710696,
                0.6277453496193508,
                0.2243092008234005,
                0.7887198549093222,
                1.526173082951801
            ],
            [
                0.04691081308716511,
                0.700709729539164,
                0.18290482775650624,
                0.7763868306837519,
                1.5455694634508885
            ],
            [
                0.050548916236903225,
                0.7713810075216448,
                0.1482685875691072,
                0.7638761841021076,
                1.5670946776026682
            ],
            [
                0.05594952567369529,
                0.8356694432532904,
                0.12253485614986225,
                0.7511398631297975,
                1.583819639974349
            ],
            [
                0.0630984163288458,
                0.8879700180737352,
                0.09904640956536052,
                0.7380380010934176,
                1.592966973120248
            ],
            [
                0.0720983220846576,
                0.9357896135767002,
                0.08164677748527989,
                0.7243392807861179,
                1.5950169049958183
            ],
            [
                0.08288156105137025,
                0.9728825950612713,
                0.06561830817458479,
                0.7094520764071255,
                1.5833297385250082
            ],
            [
                0.09471824091545289,
                0.9937247486778799,
                0.055937624002476004,
                0.693395419110569,
                1.5552371252130488
            ],
            [
                0.1074127653824852,
                0.9911154083197967,
                0.04801148580080164,
                0.6841949872125676,
                1.5141387960133261
            ],
            [
                0.12336798089382138,
                0.9718853371063018,
                0.0408404167940468,
                0.6760580660348527,
                1.4623867541289464
            ],
            [
                0.1405195332036411,
                0.9383637551038818,
                0.03493180120650443,
                0.6668437120435902,
                1.4016547572073919
            ],
            [
                0.15937142959919798,
                0.893752052283458,
                0.030388800891659046,
                0.6521548432296127,
                1.328331960574326
            ],
            [
                0.18042986013085605,
                0.8330877778848729,
                0.026856099545044396,
                0.6163655082300882,
                1.2523791229030303
            ],
            [
                0.20586517684774217,
                0.7625037936078256,
                0.023833757554252082,
                0.5609999776842278,
                1.1689815857534682
            ],
            [
                0.23349360528575833,
                0.6815395990307574,
                0.021445977730002515,
                0.4905713671519905,
                1.0735379429683505
            ],
            [
                0.26730981581024493,
                0.5948999423943411,
                0.019299121741842326,
                0.4166346964557964,
                0.9781242986660884
            ],
            [
                0.3034800396778089,
                0.5079454130834664,
                0.017405495879581314,
                0.35449925041124536,
                0.8792026349310935
            ],
            [
                0.3388401967266463,
                0.4327267510688431,
                0.016120334550845914,
                0.29780262333944746,
                0.8115832278084902
            ],
            [
                0.37581938337860754,
                0.36602568219657283,
                0.01597565272636448,
                0.25328486054479643,
                0.7661345452906674
            ],
            [
                0.4152482028725558,
                0.3027209843571191,
                0.015391115598528887,
                0.22372964928974337,
                0.7435890484153658
            ],
            [
                0.4564376967151353,
                0.2496326274794699,
                0.014755827476409505,
                0.20898132419681478,
                0.7397390474716644
            ],
            [
                0.5005911861712049,
                0.20515155799835197,
                0.013587680070708598,
                0.20357427928596275,
                0.7511032048093211
            ],
            [
                0.5438227097397845,
                0.17065290834213234,
                0.011848382176603242,
                0.20111633960211486,
                0.7727559400516065
            ],
            [
                0.5856670191971101,
                0.14253075120413483,
                0.009601310394461205,
                0.20009905828908142,
                0.8008066618299688
            ],
            [
                0.6273216706811591,
                0.12245997413139922,
                0.006821266129672916,
                0.20005838942725981,
                0.8327657626846033
            ],
            [
                0.6726974229685206,
                0.10388106984392072,
                0.004000774217521752,
                0.20050247530588394,
                0.8669369694469103
            ],
            [
                0.7180490961838759,
                0.08820662564883563,
                0.0023942496895360417,
                0.2011219119635486,
                0.9020134573898888
            ],
            [
                0.7583502429455593,
                0.0755841319300358,
                0.0011150756080241272,
                0.20107507861286583,
                0.9368926449981405
            ],
            [
                0.7988495715766735,
                0.06691180324533907,
                0.0001344126364283433,
                0.1989289192651825,
                0.9696533889072853
            ],
            [
                0.8374776148978634,
                0.0597410031334923,
                -0.0005764752606348977,
                0.196055988241469,
                1.002537332134541
            ],
            [
                0.8737122518252017,
                0.05408852300957564,
                -0.0010463241185491873,
                0.1930234868234411,
                1.031934013978701
            ],
            [
                0.9096167724126918,
                0.04953967570126168,
                -0.0013038699726981111,
                0.1899764602635246,
                1.057703816617724
            ],
            [
                0.9398732338322553,
                0.04529301060864975,
                -0.0013778488584652616,
                0.18689732918593338,
                1.0771067091149527
            ],
            [
                0.9647666118275269,
                0.041904129349914644,
                -0.0012969968112342247,
                0.18380225711058837,
                1.090092916575586
            ],
            [
                0.9776695554057638,
                0.03885585948920116,
                -0.0010900498663885929,
                0.1807078873469057,
                1.1001805182964046
            ],
            [
                0.9861270803938307,
                0.036664661615591794,
                -0.0007857440593119509,
                0.17765896424664696,
                1.108270366620763
            ],
            [
                0.993515334929022,
                0.03485566021451235,
                -0.000412815425387892,
                0.17462308816785896,
                1.1123718611542892
            ],
            [
                0.9939642142582097,
                0.03340840891250732,
                0.0,
                0.1712406333578629,
                1.1076073519231096
            ],
            [
                0.9844796439471935,
                0.032640466238101525,
                0.00042396618146813204,
                0.16875360085719943,
                1.1000572772155566
            ],
            [
                0.9676329012516397,
                0.03180230898111845,
                0.0008303470836329164,
                0.166039880593069,
                1.0855623371271113
            ],
            [
                0.9397180346616234,
                0.0316154297065389,
                0.001190406671110764,
                0.16372463278071522,
                1.064722828638494
            ],
            [
                0.9034761891993082,
                0.03052347014581009,
                0.0014754089085180864,
                NaN,
                NaN
            ],
            [
                0.8592032627736605,
                0.030578873471475213,
                0.001656617760471294,
                NaN,
                NaN
            ],
            [
                0.813300936711092,
                0.03059230743124825,
                0.001705297191586798,
                NaN,
                NaN
            ],
            [
                0.7626300660445599,
                0.02966518589805638,
                0.0015927111664810092,
                NaN,
                NaN
            ],
            [
                0.7077142240998846,
                0.029365922210930737,
                0.0012901236497703402,
                NaN,
                NaN
            ],
            [
                0.6519632053140386,
                0.028690578143049605,
                0.0007687986060712,
                NaN,
                NaN
            ],
            [
                NaN,
                0.028086758983920972,
                0.0,
                NaN,
                NaN
            ],
            [
                NaN,
                NaN,
                NaN,
                NaN,
                NaN
            ],
            [
                NaN,
                NaN,
                NaN,
                NaN,
                NaN
            ],
            [
                NaN,
                NaN,
                NaN,
                NaN,
                NaN
            ],
            [
                NaN,
                NaN,
                NaN,
                NaN,
                NaN
            ],
            [
                NaN,
                NaN,
                NaN,
                NaN,
                NaN
            ],
            [
                NaN,
                NaN,
                NaN,
                NaN,
                NaN
            ]
        ],
        "tune": {
            "gamma_factor": 1.0,
            "dye_density_min_factor": 1.0
        },
        "density_curves_layers": [
            0,
            3,
            3
        ]
    },
    "glare": {
        "active": false,
        "percent": 0.0,
        "roughness": 0.25,
        "blur": 0.5
    },
    "grain": {
        "active": true,
        "sublayers_active": true,
        "agx_particle_area_um2": 0.2,
        "agx_particle_scale": [
            0.8,
            1,
            2
        ],
        "agx_particle_scale_layers": [
            2.5,
            1,
            0.5
        ],
        "density_min": [
            0.07,
            0.08,
            0.12
        ],
        "uniformity": [
            0.97,
            0.97,
            0.99
        ],
        "blur": 0.55,
        "blur_dye_clouds_um": 1.0,
        "micro_structure": [
            0.2,
            0.5
        ],
        "n_sub_layers": 1
    },
    "halation": {
        "active": true,
        "strength": [
            0.08,
            0.005,
            0.001
        ],
        "size_um": [
            200,
            200,
            200
        ],
        "scattering_strength": [
            0.01,
            0.02,
            0.04
        ],
        "scattering_size_um": [
            30,
            20,
            15
        ]
    },
    "dir_couplers": {
        "active": true,
        "amount": 1.0,
        "ratio_rgb": [
            1.0,
            1.0,
            1.0
        ],
        "diffusion_interlayer": 2.0,
        "diffusion_size_um": 10.0,
        "high_exposure_shift": 0.0
    },
    "masking_couplers": {
        "cross_over_points": [
            585,
            510,
            200
        ],
        "transition_widths": [
            15,
            15,
            1
        ],
        "gaussian_model": [
            [
                [
                    435,
                    20,
                    0.09
                ],
                [
                    560,
                    20,
                    0.09
                ]
            ],
            [
                [
                    470,
                    20,
                    0.09
                ]
            ],
            [
                [
                    520,
                    20,
                    0.09
                ]
            ]
        ]
    }
}